{
    "project": "SmartMentor Arduino Image Collection",
    "setup_date": "2025-12-17 16:42:56",
    "total_images": 8,
    "images": [
        {
            "filename": "andon_system_Image.jpg",
            "path": "scraped_images/boards/andon_system_Image.jpg",
            "category": "boards",
            "size_kb": 68.76,
            "dimensions": "934x726",
            "format": "JPEG",
            "created": "Wed Dec 17 09:23:21 2025"
        },
        {
            "filename": "andon_system_Image.png",
            "path": "scraped_images/boards/andon_system_Image.png",
            "category": "boards",
            "size_kb": 167.1,
            "dimensions": "1736x827",
            "format": "PNG",
            "created": "Wed Dec 17 09:23:21 2025"
        },
        {
            "filename": "ERD.png",
            "path": "scraped_images/boards/ERD.png",
            "category": "boards",
            "size_kb": 74.22,
            "dimensions": "1122x806",
            "format": "PNG",
            "created": "Wed Dec 17 09:23:21 2025"
        },
        {
            "filename": "arduino_logo.png",
            "path": "scraped_images/boards/arduino_logo.png",
            "category": "boards",
            "size_kb": 17.41,
            "dimensions": "765x324",
            "format": "PNG",
            "created": "Wed Dec 17 16:42:56 2025"
        },
        {
            "filename": "uno_pinout_diagram.png",
            "path": "scraped_images/diagrams/uno_pinout_diagram.png",
            "category": "diagrams",
            "size_kb": 287.41,
            "dimensions": "2572x2572",
            "format": "PNG",
            "created": "Wed Dec 17 16:42:53 2025"
        },
        {
            "filename": "mega_pinout.jpg",
            "path": "scraped_images/diagrams/mega_pinout.jpg",
            "category": "diagrams",
            "size_kb": 365.0,
            "dimensions": "2571x2572",
            "format": "PNG",
            "created": "Wed Dec 17 09:23:21 2025"
        },
        {
            "filename": "uno_pinout.jpg",
            "path": "scraped_images/diagrams/uno_pinout.jpg",
            "category": "diagrams",
            "size_kb": 287.41,
            "dimensions": "2572x2572",
            "format": "PNG",
            "created": "Wed Dec 17 09:23:21 2025"
        },
        {
            "filename": "nano_pinout_diagram.png",
            "path": "scraped_images/diagrams/nano_pinout_diagram.png",
            "category": "diagrams",
            "size_kb": 271.36,
            "dimensions": "2571x2572",
            "format": "PNG",
            "created": "Wed Dec 17 16:42:54 2025"
        }
    ],
    "categories": {
        "boards": 4,
        "components": 0,
        "diagrams": 4
    }
}